brij/Auth.py
brij/MpesaServices.py
brij/__init__.py
brij/base.py
brij/loader.py
brij/mpesa.py
brij/urls.py
tests/__init__.py
tests/test_auth.py
tests/test_escrow.py
tests/test_to_acc.py
tests/test_validation.py
brij_fintech-0.0.7.dist-info/LICENSE.txt
brij_fintech-0.0.7.dist-info/METADATA
brij_fintech-0.0.7.dist-info/WHEEL
brij_fintech-0.0.7.dist-info/top_level.txt
brij_fintech-0.0.7.dist-info/RECORD
