Metadata-Version: 2.1
Name: brij-fintech
Version: 0.0.7
Summary: A library for brij fintech
Home-page: https://github.com/brianmuigai/brij
Author: Brian Muigai
Author-email: brianmuigai1@gmail.com
License: UNKNOWN
Platform: UNKNOWN
Classifier: Programming Language :: Python :: 3
Classifier: License :: OSI Approved :: MIT License
Classifier: Operating System :: OS Independent
Requires-Python: >=3.6
